{
  "node_modules/@sveltejs/kit/src/runtime/client/start.js": {
    "file": "app/immutable/start-17e1ec3e.js",
    "src": "node_modules/@sveltejs/kit/src/runtime/client/start.js",
    "isEntry": true,
    "imports": [
      "_index-48da590e.js",
      "_singletons-2e4c2415.js",
      "_paths-6ff7d232.js"
    ],
    "dynamicImports": [
      ".svelte-kit/generated/nodes/0.js",
      ".svelte-kit/generated/nodes/1.js",
      ".svelte-kit/generated/nodes/2.js",
      ".svelte-kit/generated/nodes/3.js",
      ".svelte-kit/generated/nodes/4.js",
      ".svelte-kit/generated/nodes/5.js"
    ]
  },
  "src/routes/+layout.svelte": {
    "file": "app/immutable/components/pages/_layout.svelte-8a5505dc.js",
    "src": "src/routes/+layout.svelte",
    "isEntry": true,
    "imports": [
      "_index-48da590e.js",
      "_paths-6ff7d232.js",
      "_stores-026e9f06.js"
    ],
    "css": [
      "app/immutable/assets/_layout-a2c216c6.css"
    ]
  },
  "node_modules/@sveltejs/kit/src/runtime/components/error.svelte": {
    "file": "app/immutable/components/error.svelte-572e80dc.js",
    "src": "node_modules/@sveltejs/kit/src/runtime/components/error.svelte",
    "isEntry": true,
    "imports": [
      "_index-48da590e.js",
      "_stores-026e9f06.js"
    ]
  },
  "src/routes/+page.svelte": {
    "file": "app/immutable/components/pages/_page.svelte-4cfe7a7e.js",
    "src": "src/routes/+page.svelte",
    "isEntry": true,
    "imports": [
      "_index-48da590e.js",
      "_paths-6ff7d232.js"
    ],
    "css": [
      "app/immutable/assets/_page-a5682ee0.css"
    ]
  },
  "src/routes/cidades/+page.svelte": {
    "file": "app/immutable/components/pages/cidades/_page.svelte-86858cd3.js",
    "src": "src/routes/cidades/+page.svelte",
    "isEntry": true,
    "imports": [
      "_index-48da590e.js"
    ],
    "css": [
      "app/immutable/assets/_page-92e40f4c.css"
    ]
  },
  "src/routes/sobre/+page.svelte": {
    "file": "app/immutable/components/pages/sobre/_page.svelte-e83d8561.js",
    "src": "src/routes/sobre/+page.svelte",
    "isEntry": true,
    "imports": [
      "_index-48da590e.js"
    ]
  },
  "src/routes/teste/+page.svelte": {
    "file": "app/immutable/components/pages/teste/_page.svelte-c2cb54f0.js",
    "src": "src/routes/teste/+page.svelte",
    "isEntry": true,
    "imports": [
      "_index-48da590e.js",
      "_paths-6ff7d232.js"
    ],
    "css": [
      "app/immutable/assets/_page-a5682ee0.css"
    ]
  },
  "_singletons-2e4c2415.js": {
    "file": "app/immutable/chunks/singletons-2e4c2415.js",
    "imports": [
      "_index-48da590e.js",
      "_paths-6ff7d232.js"
    ]
  },
  "_paths-6ff7d232.js": {
    "file": "app/immutable/chunks/paths-6ff7d232.js"
  },
  "_index-48da590e.js": {
    "file": "app/immutable/chunks/index-48da590e.js"
  },
  "_stores-026e9f06.js": {
    "file": "app/immutable/chunks/stores-026e9f06.js",
    "imports": [
      "_index-48da590e.js",
      "_singletons-2e4c2415.js"
    ]
  },
  ".svelte-kit/generated/nodes/0.js": {
    "file": "app/immutable/chunks/0-5721506e.js",
    "src": ".svelte-kit/generated/nodes/0.js",
    "isDynamicEntry": true,
    "imports": [
      "src/routes/+layout.svelte"
    ]
  },
  ".svelte-kit/generated/nodes/1.js": {
    "file": "app/immutable/chunks/1-cdc70d01.js",
    "src": ".svelte-kit/generated/nodes/1.js",
    "isDynamicEntry": true,
    "imports": [
      "node_modules/@sveltejs/kit/src/runtime/components/error.svelte"
    ]
  },
  ".svelte-kit/generated/nodes/2.js": {
    "file": "app/immutable/chunks/2-4dc909c2.js",
    "src": ".svelte-kit/generated/nodes/2.js",
    "isDynamicEntry": true,
    "imports": [
      "src/routes/+page.svelte"
    ]
  },
  ".svelte-kit/generated/nodes/3.js": {
    "file": "app/immutable/chunks/3-47a6a570.js",
    "src": ".svelte-kit/generated/nodes/3.js",
    "isDynamicEntry": true,
    "imports": [
      "src/routes/cidades/+page.svelte"
    ]
  },
  ".svelte-kit/generated/nodes/4.js": {
    "file": "app/immutable/chunks/4-c2dcfba8.js",
    "src": ".svelte-kit/generated/nodes/4.js",
    "isDynamicEntry": true,
    "imports": [
      "src/routes/sobre/+page.svelte"
    ]
  },
  ".svelte-kit/generated/nodes/5.js": {
    "file": "app/immutable/chunks/5-48f95674.js",
    "src": ".svelte-kit/generated/nodes/5.js",
    "isDynamicEntry": true,
    "imports": [
      "src/routes/teste/+page.svelte"
    ]
  },
  "src/routes/+page.css": {
    "file": "app/immutable/assets/_page-a5682ee0.css",
    "src": "src/routes/+page.css"
  },
  "src/routes/cidades/+page.css": {
    "file": "app/immutable/assets/_page-92e40f4c.css",
    "src": "src/routes/cidades/+page.css"
  },
  "src/routes/+layout.css": {
    "file": "app/immutable/assets/_layout-a2c216c6.css",
    "src": "src/routes/+layout.css"
  }
}